moodleteacher/__init__.py
moodleteacher/assignments.py
moodleteacher/compiler.py
moodleteacher/connection.py
moodleteacher/courses.py
moodleteacher/exceptions.py
moodleteacher/files.py
moodleteacher/grades.py
moodleteacher/preview.py
moodleteacher/requests.py
moodleteacher/runnable.py
moodleteacher/submissions.py
moodleteacher/users.py
moodleteacher/validation.py
moodleteacher-0.1.16.dist-info/LICENSE
moodleteacher-0.1.16.dist-info/METADATA
moodleteacher-0.1.16.dist-info/WHEEL
moodleteacher-0.1.16.dist-info/top_level.txt
moodleteacher-0.1.16.dist-info/RECORD
