Metadata-Version: 2.1
Name: moodleteacher
Version: 0.1.16
Summary: A Moodle client library for teachers.
Home-page: https://github.com/troeger/moodleteacher
Author: Peter Tröger
Author-email: peter@troeger.eu
License: BSD
Platform: UNKNOWN
Classifier: Development Status :: 4 - Beta
Classifier: Programming Language :: Python :: 3
Requires-Dist: requests
Requires-Dist: pexpect
Provides-Extra: ui
Requires-Dist: wxPython ; extra == 'ui'
Requires-Dist: PyMuPDF ; extra == 'ui'
